schmitech_orbit_client/__init__.py
schmitech_orbit_client/chat_client.py
schmitech_orbit_client-1.1.6.dist-info/METADATA
schmitech_orbit_client-1.1.6.dist-info/WHEEL
schmitech_orbit_client-1.1.6.dist-info/entry_points.txt
schmitech_orbit_client-1.1.6.dist-info/licenses/LICENSE
schmitech_orbit_client-1.1.6.dist-info/RECORD
