Metadata-Version: 2.4
Name: schmitech-orbit-client
Version: 1.1.6
Summary: An MCP Python client for interacting with Orbit chat servers
Project-URL: Homepage, https://github.com/schmitech/orbit
Author-email: Schmitech <info@schmitech.ca>
License-Expression: Apache-2.0
License-File: LICENSE
Classifier: License :: OSI Approved :: Apache Software License
Classifier: Operating System :: OS Independent
Classifier: Programming Language :: Python :: 3
Requires-Python: >=3.11
Requires-Dist: colorama>=0.4.6
Requires-Dist: httpx>=0.28.1
Requires-Dist: prompt-toolkit>=3.0.52
Requires-Dist: requests>=2.31.0
Requires-Dist: rich>=14.1.0
